coreason_protocol/__init__.py
coreason_protocol/compiler.py
coreason_protocol/interfaces.py
coreason_protocol/main.py
coreason_protocol/server.py
coreason_protocol/service.py
coreason_protocol/types.py
coreason_protocol/utils/__init__.py
coreason_protocol/utils/logger.py
coreason_protocol/validator.py
coreason_protocol-0.3.0.dist-info/METADATA
coreason_protocol-0.3.0.dist-info/WHEEL
coreason_protocol-0.3.0.dist-info/licenses/LICENSE
coreason_protocol-0.3.0.dist-info/licenses/NOTICE
coreason_protocol-0.3.0.dist-info/RECORD
