Metadata-Version: 2.4
Name: coreason-protocol
Version: 0.3.0
Summary: Design and Governance Engine for high-stakes research.
License-File: LICENSE
License-File: NOTICE
Author: Gowtham A Rao
Author-email: gowtham.rao@coreason.ai
Requires-Python: >=3.11,<3.15
Classifier: Programming Language :: Python :: 3
Classifier: Programming Language :: Python :: 3.11
Classifier: Programming Language :: Python :: 3.12
Classifier: Programming Language :: Python :: 3.13
Classifier: Programming Language :: Python :: 3.14
Requires-Dist: aiofiles (>=25.1.0,<26.0.0)
Requires-Dist: anyio (>=4.12.1,<5.0.0)
Requires-Dist: boolean-py (>=5.0,<6.0)
Requires-Dist: coreason-identity (>=0.4.2,<0.5.0)
Requires-Dist: fastapi
Requires-Dist: httpx (>=0.28.1,<0.29.0)
Requires-Dist: loguru (>=0.7.0,<0.8.0)
Requires-Dist: pydantic (>=2.0,<3.0)
Requires-Dist: uvicorn[standard]
